README.md
package_info.json
setup.py
th2_grpc_sim/__init__.py
th2_grpc_sim/sim.proto
th2_grpc_sim/sim_pb2.py
th2_grpc_sim/sim_pb2_grpc.py
th2_grpc_sim/sim_service.py
th2_grpc_sim.egg-info/PKG-INFO
th2_grpc_sim.egg-info/SOURCES.txt
th2_grpc_sim.egg-info/dependency_links.txt
th2_grpc_sim.egg-info/requires.txt
th2_grpc_sim.egg-info/top_level.txt