Metadata-Version: 2.1
Name: th2-grpc-sim
Version: 2.2.2
Summary: th2_grpc_sim
Home-page: https://github.com/th2-net/th2-grpc-sim
Author: TH2-devs
Author-email: th2-devs@exactprosystems.com
License: Apache License 2.0
Platform: UNKNOWN
Requires-Python: >=3.7
